{"name":"MiastoX","className":"DataModel","filePaths":["default.project.json"],"children":[{"name":"Packages","className":"Folder","children":[{"name":"_Index","className":"Folder","children":[{"name":"evaera_promise@4.0.0","className":"Folder","children":[{"name":"promise","className":"ModuleScript","filePaths":["Packages\\_Index\\evaera_promise@4.0.0\\promise\\lib\\init.lua","Packages\\_Index\\evaera_promise@4.0.0\\promise\\default.project.json"],"children":[{"name":"init.spec","className":"ModuleScript","filePaths":["Packages\\_Index\\evaera_promise@4.0.0\\promise\\lib\\init.spec.lua"]}]}]},{"name":"reselim_base64@3.0.0","className":"Folder","children":[{"name":"base64","className":"ModuleScript","filePaths":["Packages\\_Index\\reselim_base64@3.0.0\\base64\\Base64.lua","Packages\\_Index\\reselim_base64@3.0.0\\base64\\default.project.json"]}]},{"name":"sleitnick_signal@2.0.1","className":"Folder","children":[{"name":"signal","className":"ModuleScript","filePaths":["Packages\\_Index\\sleitnick_signal@2.0.1\\signal\\init.lua"],"children":[{"name":"init.spec","className":"ModuleScript","filePaths":["Packages\\_Index\\sleitnick_signal@2.0.1\\signal\\init.spec.lua"]},{"name":"wally","className":"ModuleScript","filePaths":["Packages\\_Index\\sleitnick_signal@2.0.1\\signal\\wally.toml"]}]}]},{"name":"sleitnick_trove@1.5.0","className":"Folder","children":[{"name":"trove","className":"ModuleScript","filePaths":["Packages\\_Index\\sleitnick_trove@1.5.0\\trove\\init.luau"],"children":[{"name":"init.spec","className":"ModuleScript","filePaths":["Packages\\_Index\\sleitnick_trove@1.5.0\\trove\\init.spec.luau"]},{"name":"wally","className":"ModuleScript","filePaths":["Packages\\_Index\\sleitnick_trove@1.5.0\\trove\\wally.toml"]}]}]}]},{"name":"base64","className":"ModuleScript","filePaths":["Packages\\base64.lua"]},{"name":"promise","className":"ModuleScript","filePaths":["Packages\\promise.lua"]},{"name":"signal","className":"ModuleScript","filePaths":["Packages\\signal.lua"]},{"name":"trove","className":"ModuleScript","filePaths":["Packages\\trove.lua"]}]},{"name":"ReplicatedStorage","className":"ReplicatedStorage","children":[{"name":"Shared","className":"Folder","children":[{"name":"Hello","className":"ModuleScript","filePaths":["src/shared\\Hello.luau"]}]}]},{"name":"ServerScriptService","className":"ServerScriptService","children":[{"name":"Server","className":"Script","filePaths":["src/server\\init.server.luau"]}]},{"name":"StarterPlayer","className":"StarterPlayer","children":[{"name":"StarterPlayerScripts","className":"StarterPlayerScripts","children":[{"name":"Client","className":"LocalScript","filePaths":["src/client\\init.client.luau"]}]}]}]}